pe_tools/__init__.py
pe_tools/cvinfo.py
pe_tools/pdb.py
pe_tools/pe_parser.py
pe_tools/peresed.py
pe_tools/rsrc.py
pe_tools/struct3.py
pe_tools/utils.py
pe_tools/version_info.py
pe_tools-0.3.10.dist-info/LICENSE
pe_tools-0.3.10.dist-info/METADATA
pe_tools-0.3.10.dist-info/WHEEL
pe_tools-0.3.10.dist-info/entry_points.txt
pe_tools-0.3.10.dist-info/top_level.txt
pe_tools-0.3.10.dist-info/RECORD
