Metadata-Version: 2.1
Name: pe-tools
Version: 0.3.10
Summary: UNKNOWN
Home-page: https://github.com/avast/pe_tools
Maintainer: Martin Vejnár
Maintainer-email: martin.vejnar@avast.com
License: UNKNOWN
Platform: UNKNOWN
Requires-Dist: grope
